five9/__init__.py
five9/api/__init__.py
five9/api/base_client.py
five9/api/client_v6.py
five9/api/v6_datastores.py
five9/api/v6_prompts.py
five9/api/v6_tasks.py
five9/models/__init__.py
five9/models/common.py
five9/models/query_filter.py
five9_python-0.0.3.dist-info/LICENSE
five9_python-0.0.3.dist-info/METADATA
five9_python-0.0.3.dist-info/WHEEL
five9_python-0.0.3.dist-info/top_level.txt
five9_python-0.0.3.dist-info/RECORD
