Metadata-Version: 2.1
Name: five9-python
Version: 0.0.3
Summary: A Python SDK for working with Five9 CCaaS API's
License: MIT License
Project-URL: Homepage, https://github.com/James-Smart/five9-python
Keywords: Five9,CCaaS
Classifier: Development Status :: 2 - Pre-Alpha
Classifier: Intended Audience :: Developers
Classifier: License :: OSI Approved :: MIT License
Classifier: Programming Language :: Python :: 3
Classifier: Programming Language :: Python :: 3.8
Classifier: Programming Language :: Python :: 3.9
Classifier: Programming Language :: Python :: 3.10
Classifier: Programming Language :: Python :: 3.11
Classifier: Programming Language :: Python :: 3 :: Only
Requires-Python: >=3.8
License-File: LICENSE
Requires-Dist: requests-ratelimiter
Requires-Dist: requests
